{
  "$schema": "https://developer.microsoft.com/json-schemas/fabric/item/report/definition/visualContainer/1.5.0/schema.json",
  "name": "7de58b708d75d62780ae",
  "position": {
    "x": 711.11111111111109,
    "y": 470.75555555555553,
    "z": 3000,
    "height": 153.6,
    "width": 391.11111111111109,
    "tabOrder": 3000
  },
  "visual": {
    "visualType": "card",
    "query": {
      "queryState": {
        "Values": {
          "projections": [
            {
              "field": {
                "Measure": {
                  "Expression": {
                    "SourceRef": {
                      "Entity": "100_Sales_Records"
                    }
                  },
                  "Property": "MaxDate"
                }
              },
              "queryRef": "100_Sales_Records.MaxDate",
              "nativeQueryRef": "MaxDate"
            }
          ]
        }
      },
      "sortDefinition": {
        "sort": [
          {
            "field": {
              "Measure": {
                "Expression": {
                  "SourceRef": {
                    "Entity": "100_Sales_Records"
                  }
                },
                "Property": "MaxDate"
              }
            },
            "direction": "Ascending"
          }
        ],
        "isDefaultSort": true
      }
    },
    "drillFilterOtherVisuals": true
  }
}